runicorn/__init__.py
runicorn/cli.py
runicorn/config.py
runicorn/environment.py
runicorn/experiment.py
runicorn/exporters.py
runicorn/monitors.py
runicorn/sdk.py
runicorn/ssh_connection_manager.py
runicorn/ssh_host_keys.py
runicorn/ssh_sync.py
runicorn/ssh_sync_improved.py
runicorn/viewer.py
runicorn/artifacts/__init__.py
runicorn/artifacts/artifact.py
runicorn/artifacts/lineage.py
runicorn/artifacts/models.py
runicorn/artifacts/storage.py
runicorn/remote_storage/__init__.py
runicorn/remote_storage/adapter.py
runicorn/remote_storage/adapter_unified.py
runicorn/remote_storage/cache_manager.py
runicorn/remote_storage/file_fetcher.py
runicorn/remote_storage/metadata_sync.py
runicorn/remote_storage/models.py
runicorn/remote_storage/remote_executor.py
runicorn/security/__init__.py
runicorn/security/credentials.py
runicorn/security/path_validation.py
runicorn/security/rate_limiter.py
runicorn/storage/__init__.py
runicorn/storage/backends.py
runicorn/storage/migration.py
runicorn/storage/models.py
runicorn/storage/sql_utils.py
runicorn/storage/sync_utils.py
runicorn/viewer/__init__.py
runicorn/viewer/api/__init__.py
runicorn/viewer/api/artifacts.py
runicorn/viewer/api/config.py
runicorn/viewer/api/experiment_artifacts.py
runicorn/viewer/api/experiments.py
runicorn/viewer/api/export.py
runicorn/viewer/api/gpu.py
runicorn/viewer/api/health.py
runicorn/viewer/api/import_.py
runicorn/viewer/api/metrics.py
runicorn/viewer/api/model_lifecycle.py
runicorn/viewer/api/projects.py
runicorn/viewer/api/remote_storage.py
runicorn/viewer/api/runs.py
runicorn/viewer/api/ssh.py
runicorn/viewer/api/ui_preferences.py
runicorn/viewer/api/unified_ssh.py
runicorn/viewer/api/v2/__init__.py
runicorn/viewer/api/v2/analytics.py
runicorn/viewer/api/v2/experiments.py
runicorn/viewer/middleware/__init__.py
runicorn/viewer/middleware/rate_limit.py
runicorn/viewer/services/__init__.py
runicorn/viewer/services/gpu.py
runicorn/viewer/services/modern_storage.py
runicorn/viewer/services/storage.py
runicorn-0.4.1.dist-info/licenses/LICENSE
runicorn-0.4.1.dist-info/METADATA
runicorn-0.4.1.dist-info/WHEEL
runicorn-0.4.1.dist-info/entry_points.txt
runicorn-0.4.1.dist-info/top_level.txt
runicorn-0.4.1.dist-info/RECORD
