Metadata-Version: 2.4
Name: runicorn
Version: 0.4.1
Summary: Local experiment tracking with model versioning - self-hosted W&B alternative with Artifacts
Author: Runicorn Authors
License-Expression: MIT
Project-URL: Homepage, https://pypi.org/project/runicorn/
Project-URL: Changelog, https://pypi.org/project/runicorn/#history
Keywords: experiment-tracking,mlops,training,visualization,fastapi,wandb-alternative,self-hosted
Classifier: Programming Language :: Python :: 3
Classifier: Programming Language :: Python :: 3.8
Classifier: Programming Language :: Python :: 3.9
Classifier: Programming Language :: Python :: 3.10
Classifier: Programming Language :: Python :: 3.11
Classifier: Programming Language :: Python :: 3.12
Classifier: Programming Language :: Python :: 3.13
Classifier: Framework :: FastAPI
Classifier: Intended Audience :: Science/Research
Classifier: Topic :: Scientific/Engineering :: Artificial Intelligence
Classifier: Topic :: Software Development :: Quality Assurance
Classifier: Environment :: Web Environment
Classifier: Operating System :: OS Independent
Requires-Python: >=3.8
License-File: LICENSE
Requires-Dist: fastapi<1.0,>=0.110
Requires-Dist: uvicorn[standard]<0.31,>=0.23
Requires-Dist: pydantic<3,>=2
Requires-Dist: aiofiles<24,>=23
Requires-Dist: filelock>=3.12
Requires-Dist: paramiko<4,>=3.3
Requires-Dist: psutil>=5.8.0
Requires-Dist: httpx
Provides-Extra: images
Requires-Dist: pillow>=9; extra == "images"
Requires-Dist: numpy>=1.22; extra == "images"
Requires-Dist: matplotlib>=3.6; extra == "images"
Dynamic: license-file
